oneai_cli/__init__.py
oneai_cli/main.py
oneai_cli/start.py
oneai_cli/stop.py
oneai_cli/test.py
oneai_cli/train.py
oneai_cli/utils.py
oneai_cli/parsers/__init__.py
oneai_cli/parsers/general.py
oneai_cli/parsers/server.py
oneai_cli/parsers/test.py
oneai_cli/parsers/train.py
oneai_cli-0.2.dist-info/LICENSE
oneai_cli-0.2.dist-info/METADATA
oneai_cli-0.2.dist-info/WHEEL
oneai_cli-0.2.dist-info/entry_points.txt
oneai_cli-0.2.dist-info/top_level.txt
oneai_cli-0.2.dist-info/RECORD
