Metadata-Version: 2.1
Name: oneai-cli
Version: 0.2
Summary: OneAIOps CLI
Author-email: OpenNebula Systems <contact@opennebula.io>
Maintainer-email: OpenNebula Systems <contact@opennebula.io>
License:                                  Apache License
Project-URL: Source, https://github.com/OpenNebula/one-aiops
Project-URL: Bug Tracker, https://github.com/OpenNebula/one-aiops/issues
Project-URL: Wiki, https://github.com/OpenNebula/one-aiops/wiki
Keywords: AIOps,Cloud Computing,Scheduling,Workload Optimization,Anomaly detection
Classifier: Development Status :: 3 - Alpha
Classifier: Intended Audience :: Developers
Classifier: Topic :: Software Development :: Build Tools
Classifier: License :: OSI Approved :: Apache Software License
Classifier: Programming Language :: Python :: 3
Requires-Python: >=3.11
License-File: LICENSE
Requires-Dist: pyoneai
Requires-Dist: pyoneai-ops
Requires-Dist: rich
